metorial_mcp_session/__init__.py
metorial_mcp_session/_silence_sse_noise.py
metorial_mcp_session/mcp_client.py
metorial_mcp_session/mcp_session.py
metorial_mcp_session/mcp_tool.py
metorial_mcp_session/mcp_tool_manager.py
metorial_mcp_session-1.0.3.dist-info/METADATA
metorial_mcp_session-1.0.3.dist-info/WHEEL
metorial_mcp_session-1.0.3.dist-info/licenses/LICENSE
metorial_mcp_session-1.0.3.dist-info/RECORD
